src/lm_identifier/__init__.py
src/lm_identifier/core.py
src/lm_identifier/utils.py
lm_identifier-0.0.1.dist-info/LICENSE
lm_identifier-0.0.1.dist-info/WHEEL
lm_identifier-0.0.1.dist-info/METADATA
lm_identifier-0.0.1.dist-info/RECORD
