Metadata-Version: 2.1
Name: lm-identifier
Version: 0.0.1
Summary: A toolkit for identifying pretrained language models from AI-generated text
License: MIT
Author: Jaesung Tae
Author-email: jaesungtae@gmail.com
Requires-Python: >=3.8,<4.0
Classifier: License :: OSI Approved :: MIT License
Classifier: Programming Language :: Python :: 3
Classifier: Programming Language :: Python :: 3.8
Classifier: Programming Language :: Python :: 3.9
Classifier: Programming Language :: Python :: 3.10
Classifier: Programming Language :: Python :: 3.11
Requires-Dist: numpy (>=1.24.1,<2.0.0)
Requires-Dist: torch (>=1.13.1,<2.0.0)
Requires-Dist: transformers (>=4.25.1,<5.0.0)
